{
  "schema_version": "1.0",
  "pm": "gradle",
  "pm_version_tested": "9.0.0",
  "source_file": "https://github.com/mend-detection-qa/gradle9-toolchain-only/blob/main/build.gradle",
  "root": {
    "name": "com.poc:poc-parent",
    "version": "1.0.0-SNAPSHOT",
    "dependencies": [
      {
        "name": "org.apache.commons:commons-lang3",
        "version": "3.14.0",
        "scope": "compile",
        "direct": true,
        "dependencies": []
      },
      {
        "name": "com.google.guava:guava",
        "version": "33.2.1-jre",
        "scope": "compile",
        "direct": true,
        "dependencies": [
          {
            "name": "com.google.guava:failureaccess",
            "version": "1.0.2",
            "scope": "compile",
            "direct": false,
            "dependencies": []
          },
          {
            "name": "com.google.guava:listenablefuture",
            "version": "9999.0-empty-to-avoid-conflict-with-guava",
            "scope": "compile",
            "direct": false,
            "dependencies": []
          },
          {
            "name": "com.google.code.findbugs:jsr305",
            "version": "3.0.2",
            "scope": "compile",
            "direct": false,
            "dependencies": []
          },
          {
            "name": "org.checkerframework:checker-qual",
            "version": "3.42.0",
            "scope": "compile",
            "direct": false,
            "dependencies": []
          },
          {
            "name": "com.google.errorprone:error_prone_annotations",
            "version": "2.26.1",
            "scope": "compile",
            "direct": false,
            "dependencies": []
          },
          {
            "name": "com.google.j2objc:j2objc-annotations",
            "version": "3.0.0",
            "scope": "compile",
            "direct": false,
            "dependencies": []
          }
        ]
      }
    ]
  }
}
